tinyserver/__init__.py
tinyserver-0.0.2.dist-info/LICENSE
tinyserver-0.0.2.dist-info/METADATA
tinyserver-0.0.2.dist-info/WHEEL
tinyserver-0.0.2.dist-info/top_level.txt
tinyserver-0.0.2.dist-info/RECORD
